monasca_predictor/__init__.py
monasca_predictor/daemon.py
monasca_predictor/version.py
monasca_predictor/api/__init__.py
monasca_predictor/api/monasca_api.py
monasca_predictor/common/__init__.py
monasca_predictor/common/config.py
monasca_predictor/common/util.py
monasca_predictor/inference/__init__.py
monasca_predictor/inference/model.py
monasca_predictor-0.2.0.dist-info/LICENSE
monasca_predictor-0.2.0.dist-info/METADATA
monasca_predictor-0.2.0.dist-info/WHEEL
monasca_predictor-0.2.0.dist-info/entry_points.txt
monasca_predictor-0.2.0.dist-info/pbr.json
monasca_predictor-0.2.0.dist-info/top_level.txt
monasca_predictor-0.2.0.dist-info/RECORD
