Metadata-Version: 2.1
Name: monasca-predictor
Version: 0.2.0
Summary: Integrating with Monasca to provide OpenStack with predictive analytics.
Home-page: https://github.com/giacomolanciano/monasca-predictor
Maintainer: Giacomo Lanciano
Maintainer-email: giacomo.lanciano@sns.it
License: Apache-2
Keywords: auto-scaling,cloud computing,devops,elasticity control,forecasting,monasca,monitoring,openstack,operations,predictive analytics,time-series
Platform: UNKNOWN
Classifier: Development Status :: 2 - Pre-Alpha
Classifier: License :: OSI Approved :: Apache Software License
Classifier: Topic :: System :: Monitoring
Classifier: Operating System :: POSIX :: Linux
Classifier: Programming Language :: Python :: 3
Classifier: Programming Language :: Python :: 3.7
Classifier: Programming Language :: Python :: 3 :: Only
Classifier: Programming Language :: Python :: Implementation :: CPython
Requires-Python: >=3.7
License-File: LICENSE
Requires-Dist: keystoneauth1 (<4.1.0,>=4.0.0)
Requires-Dist: monasca-agent (<4.0.0,>=3.0.2)
Requires-Dist: monasca-common (<3.2.0,>=3.1.0)
Requires-Dist: pandas (<1.2.5,>=1.0.0)
Requires-Dist: python-monascaclient (<2.2.0,>=2.1.0)
Requires-Dist: scikit-learn (<1.0,>=0.24)
Requires-Dist: six (>=1.10.0)
Requires-Dist: statsmodels (==0.13.1)
Requires-Dist: tensorflow (>=2.0)
Requires-Dist: torch (==1.8.1)
